[{"id": "fsx_S_0011", "format": "A"}, {"id": "fsx_S_0012", "format": "A"}, {"id": "fsx_S_0013", "format": "A"}, {"id": "fsx_S_0014", "format": "A"}, {"id": "fsx_S_0015", "format": "A"}, {"id": "fsx_S_0016", "format": "A"}, {"id": "fsx_S_0017", "format": "A"}, {"id": "fsx_S_0018", "format": "A"}, {"id": "fsx_S_0019", "format": "A"}, {"id": "fsx_S_0020", "format": "A"}, {"id": "fsx_S_0021", "format": "A"}, {"id": "fsx_S_0022", "format": "A"}, {"id": "fsx_S_0023", "format": "A"}, {"id": "fsx_S_0024", "format": "A"}, {"id": "fsx_S_0025", "format": "A"}, {"id": "fsx_S_0026", "format": "A"}, {"id": "fsx_S_0027", "format": "A"}, {"id": "fsx_S_0028", "format": "A"}, {"id": "fsx_S_0029", "format": "A"}, {"id": "fsx_S_0030", "format": "A"}, {"id": "fsx_S_0031", "format": "A"}, {"id": "fsx_S_0032", "format": "A"}, {"id": "fsx_S_0033", "format": "A"}, {"id": "fsx_S_0034", "format": "A"}, {"id": "fsx_S_0035", "format": "A"}, {"id": "fsx_S_0036", "format": "A"}, {"id": "fsx_S_0037", "format": "A"}, {"id": "fsx_S_0038", "format": "A"}, {"id": "fsx_S_0039", "format": "A"}, {"id": "fsx_S_0040", "format": "A"}, {"id": "fsx_S_0041", "format": "A"}, {"id": "fsx_S_0042", "format": "A"}, {"id": "fsx_S_0043", "format": "A"}, {"id": "fsx_S_0044", "format": "A"}, {"id": "fsx_S_0045", "format": "A"}, {"id": "fsx_S_0046", "format": "A"}, {"id": "fsx_S_0047", "format": "A"}, {"id": "fsx_S_0048", "format": "A"}, {"id": "fsx_S_0049", "format": "A"}, {"id": "fsx_S_0050", "format": "A"}, {"id": "fsx_S_0051", "format": "A"}, {"id": "fsx_S_0052", "format": "A"}, {"id": "fsx_S_0053", "format": "A"}, {"id": "fsx_S_0054", "format": "A"}, {"id": "fsx_S_0055", "format": "A"}, {"id": "fsx_S_0056", "format": "A"}, {"id": "fsx_S_0057", "format": "A"}, {"id": "fsx_S_0058", "format": "A"}, {"id": "fsx_S_0059", "format": "A"}, {"id": "fsx_S_0060", "format": "A"}, {"id": "fsx_S_0061", "format": "A"}, {"id": "fsx_S_0062", "format": "A"}, {"id": "fsx_S_0063", "format": "A"}, {"id": "fsx_S_0064", "format": "A"}, {"id": "fsx_S_0065", "format": "A"}, {"id": "fsx_S_0066", "format": "A"}, {"id": "fsx_S_0067", "format": "A"}, {"id": "fsx_S_0068", "format": "A"}, {"id": "fsx_S_0069", "format": "A"}, {"id": "fsx_S_0070", "format": "A"}, {"id": "fsx_S_0071", "format": "A"}, {"id": "fsx_S_0072", "format": "A"}, {"id": "fsx_S_0073", "format": "A"}, {"id": "fsx_S_0074", "format": "A"}, {"id": "fsx_S_0075", "format": "A"}, {"id": "fsx_S_0076", "format": "A"}, {"id": "fsx_S_0077", "format": "A"}, {"id": "fsx_S_0078", "format": "A"}, {"id": "fsx_S_0079", "format": "A"}, {"id": "fsx_S_0080", "format": "A"}, {"id": "fsx_A_0105", "format": "C"}, {"id": "fsx_A_0106", "format": "C"}, {"id": "fsx_A_0107", "format": "C"}, {"id": "fsx_A_0108", "format": "D"}, {"id": "fsx_A_0109", "format": "C"}, {"id": "fsx_A_0110", "format": "B"}, {"id": "fsx_A_0111", "format": "C"}, {"id": "fsx_A_0112", "format": "B"}, {"id": "fsx_A_0113", "format": "C"}, {"id": "fsx_A_0114", "format": "C"}, {"id": "fsx_A_0115", "format": "C"}, {"id": "fsx_A_0116", "format": "C"}, {"id": "fsx_A_0117", "format": "C"}, {"id": "fsx_A_0118", "format": "D"}, {"id": "fsx_A_0119", "format": "C"}, {"id": "fsx_A_0120", "format": "B"}, {"id": "fsx_A_0121", "format": "C"}, {"id": "fsx_A_0122", "format": "B"}, {"id": "fsx_A_0123", "format": "C"}, {"id": "fsx_A_0124", "format": "C"}, {"id": "fsx_A_0125", "format": "C"}, {"id": "fsx_A_0126", "format": "C"}, {"id": "fsx_A_0127", "format": "C"}, {"id": "fsx_A_0128", "format": "D"}, {"id": "fsx_A_0129", "format": "C"}, {"id": "fsx_A_0130", "format": "B"}, {"id": "fsx_A_0131", "format": "C"}, {"id": "fsx_A_0132", "format": "B"}, {"id": "fsx_A_0133", "format": "C"}, {"id": "fsx_A_0134", "format": "C"}, {"id": "fsx_A_0135", "format": "C"}, {"id": "fsx_A_0136", "format": "C"}, {"id": "fsx_A_0137", "format": "C"}, {"id": "fsx_A_0138", "format": "D"}, {"id": "fsx_A_0139", "format": "C"}, {"id": "fsx_A_0140", "format": "B"}, {"id": "fsx_A_0141", "format": "C"}, {"id": "fsx_A_0142", "format": "B"}, {"id": "fsx_A_0143", "format": "C"}, {"id": "fsx_A_0144", "format": "C"}, {"id": "fsx_A_0145", "format": "C"}, {"id": "fsx_A_0146", "format": "C"}, {"id": "fsx_A_0147", "format": "C"}, {"id": "fsx_A_0148", "format": "D"}, {"id": "fsx_A_0149", "format": "C"}, {"id": "fsx_A_0150", "format": "B"}, {"id": "fsx_B_0158", "format": "B"}, {"id": "fsx_B_0159", "format": "B"}, {"id": "fsx_B_0160", "format": "B"}, {"id": "fsx_B_0161", "format": "B"}, {"id": "fsx_B_0162", "format": "D"}, {"id": "fsx_B_0163", "format": "E"}, {"id": "fsx_B_0164", "format": "E"}, {"id": "fsx_B_0165", "format": "B"}, {"id": "fsx_B_0166", "format": "B"}, {"id": "fsx_B_0167", "format": "B"}, {"id": "fsx_B_0168", "format": "B"}, {"id": "fsx_B_0169", "format": "B"}, {"id": "fsx_B_0170", "format": "D"}, {"id": "fsx_B_0171", "format": "E"}, {"id": "fsx_B_0172", "format": "E"}, {"id": "fsx_B_0173", "format": "B"}, {"id": "fsx_B_0174", "format": "B"}, {"id": "fsx_B_0175", "format": "B"}, {"id": "fsx_B_0176", "format": "B"}, {"id": "fsx_B_0177", "format": "B"}, {"id": "fsx_B_0178", "format": "D"}, {"id": "fsx_B_0179", "format": "E"}, {"id": "fsx_B_0180", "format": "E"}, {"id": "fsx_C_0185", "format": "B"}, {"id": "fsx_C_0186", "format": "C"}, {"id": "fsx_C_0187", "format": "B"}, {"id": "fsx_C_0188", "format": "B"}, {"id": "fsx_C_0189", "format": "B"}, {"id": "fsx_C_0190", "format": "B"}, {"id": "fsx_C_0191", "format": "B"}, {"id": "fsx_C_0192", "format": "C"}, {"id": "fsx_C_0193", "format": "B"}, {"id": "fsx_C_0194", "format": "B"}, {"id": "fsx_C_0195", "format": "B"}, {"id": "fsx_C_0196", "format": "B"}, {"id": "fsx_C_0197", "format": "B"}, {"id": "fsx_C_0198", "format": "C"}, {"id": "fsx_C_0199", "format": "B"}, {"id": "fsx_C_0200", "format": "B"}]